{
  "RMRPG": {
    "Item": {
      "Name": "Item Name",
      "Chat": "Chat",
      "Feat": {
        "RequirementField": "Advantage Requirement",
        "Requirements": "Requirements",
        "Rank": "Rank",
        "Description": "Description"
      },
      "Equipment": {
        "Weight": "Weight",
        "Quantity": "Quantity",
        "Status": "Status"
      },
      "Status": {
        "Stowed": "Stowed",
        "InHand": "In Hand",
        "Dropped": "Dropped"
      },
      "Weapon": {
        "Summary": "Summary",
        "DescriptionTab": "Description",
        "DetailsTab": "Details",
        "Price": "Price",
        "CategoryLabel": "Weapon type",
        "RangeLabel": "Range",
        "HitTitle": "Hit",
        "AttributeMod": "Attribute Modifier",
        "BonusLabel": "Name",
        "BonusValue": "Bonus",
        "AddBonus": "Add custom bonus",
        "DamageTitle": "Damage",
        "NoAttribute": "No attribute",
        "DiceCount": "Quantity",
        "DieType": "Die",
        "DamageTypeLabel": "Damage type",
        "FormulaLabel": "Formula",
        "AddDamage": "Add damage",
        "Remove": "Remove",
        "Category": {
          "Melee": "Melee",
          "Ranged": "Ranged",
          "Thrown": "Thrown"
        },
        "Range": {
          "Melee": "Melee"
        },
        "DamageType": {
          "Physical": "Physical",
          "Elemental": "Elemental",
          "Mental": "Mental",
          "Deteriorating": "Deteriorating",
          "None": "No type"
        }
      },
      "Action": {
        "Cost": {
          "Label": "Action Cost",
          "Free": "Free action",
          "One": "1 action",
          "Two": "2 actions",
          "Three": "3 actions",
          "Reaction": "Reaction"
        }
      },
      "Tags": {
        "Add": "Add tag",
        "Remove": "Remove tag",
        "Placeholder": "New tag"
      },
      "Ability": {
        "Cost": "Cost",
        "TotalCost": "Total PC Cost",
        "TotalCostShort": "PC",
        "DescriptionTab": "Description",
        "DetailsTab": "Details",
        "Remove": "Remove",
        "CastingTime": {
          "Title": "Casting Time",
          "Label": "Casting Time",
          "OneAction": "1 Action",
          "TwoActions": "2 Actions",
          "ThreeActions": "3 Actions",
          "FreeAction": "Free Action",
          "Reaction": "Reaction"
        },
        "CastingCost": {
          "Title": "Ability Cost",
          "Default": "Default (1 reiki check)",
          "EnhancedCheck": "Enhanced check",
          "Free": "Free"
        },
        "Categories": {
          "Title": "Category Effects",
          "Add": "Add Category Effect",
          "LimitExceededWarning": "Category limit exceeded",
          "TableName": "Effect",
          "TableCategory": "Category",
          "TableCost": "PC Cost",
          "Empty": "No category effects yet.",
          "DropHint": "Drag category effect items here."
        },
        "Category": {
          "Criacao": "Creation",
          "Evocao": "Evocation",
          "Identificacao": "Identification",
          "Omissao": "Omission",
          "ManipulacaoMental": "Mental Manipulation",
          "Reforco": "Reinforcement",
          "Recuperacao": "Recovery"
        },
        "CategoryTooltip": {
          "Criacao": "Placeholder tooltip for Creation.",
          "Evocao": "Placeholder tooltip for Evocation.",
          "Identificacao": "Placeholder tooltip for Identification.",
          "Omissao": "Placeholder tooltip for Omission.",
          "ManipulacaoMental": "Placeholder tooltip for Mental Manipulation.",
          "Reforco": "Placeholder tooltip for Reinforcement.",
          "Recuperacao": "Placeholder tooltip for Recovery."
        },
        "Characteristics": {
          "Title": "Characteristics",
          "Add": "Add Characteristic",
          "CharacteristicLabel": "Characteristic",
          "LevelLabel": "Level",
          "EditLevelHint": "Click to edit the base level",
          "TypeLabel": "Type",
          "PCLabel": "PC",
          "RankLabel": "Rank",
          "LimitExceededWarning": "Characteristic limit exceeded",
          "OverRankingLegend": "Over-ranking characteristics"
        },
        "Characteristic": {
          "Alvos": "Targets",
          "Area": "Area",
          "Condicao": "Condition",
          "Destruicao": "Destruction",
          "Distancia": "Distance",
          "Duracao": "Duration"
        },
        "AreaType": {
          "Emanacao": "Emanation",
          "Feixe": "Beam",
          "Explosao": "Explosion",
          "Line": "Line"
        },
        "CharacteristicLevel": {
          "Targets1": "Targets 1",
          "Targets2": "Targets 2",
          "Targets3": "Targets 3",
          "Targets4": "Targets 4",
          "Targets5": "Targets 5",
          "AreaSmall": "Small Area",
          "AreaMedium": "Medium Area",
          "AreaLarge": "Large Area",
          "ConditionGrade1": "Grade 1",
          "ConditionGrade2": "Grade 2",
          "ConditionGrade3": "Grade 3",
          "ConditionGrade4": "Grade 4",
          "DurationInstant": "Instant",
          "DurationScene": "Scene",
          "DurationHours": "Hours",
          "DurationDay": "Day",
          "DurationPermanent": "Permanent",
          "DestructionNoDie": "No die",
          "DestructionD4": "d4",
          "DestructionD6": "d6",
          "DestructionD8": "d8",
          "DestructionD10": "d10",
          "DestructionD12": "d12",
          "DistanceMelee": "Melee",
          "Distance3": "3",
          "Distance6": "6",
          "Distance9": "9",
          "Distance12": "12",
          "Distance15": "15",
          "Distance18": "18",
          "Distance21": "21",
          "Distance24": "24",
          "Distance27": "27",
          "Distance30": "30"
        },
        "CharacteristicLevelShort": {
          "Targets1": "1",
          "Targets2": "2",
          "Targets3": "3",
          "Targets4": "4",
          "Targets5": "5",
          "AreaSmall": "Small",
          "AreaMedium": "Medium",
          "AreaLarge": "Large",
          "ConditionGrade1": "Grade 1",
          "ConditionGrade2": "Grade 2",
          "ConditionGrade3": "Grade 3",
          "ConditionGrade4": "Grade 4",
          "DurationInstant": "Instant",
          "DurationScene": "Scene",
          "DurationHours": "Hours",
          "DurationDay": "Day",
          "DurationPermanent": "Permanent",
          "DestructionNoDie": "No die",
          "DestructionD4": "d4",
          "DestructionD6": "d6",
          "DestructionD8": "d8",
          "DestructionD10": "d10",
          "DestructionD12": "d12",
          "DistanceMelee": "Melee",
          "Distance3": "3",
          "Distance6": "6",
          "Distance9": "9",
          "Distance12": "12",
          "Distance15": "15",
          "Distance18": "18",
          "Distance21": "21",
          "Distance24": "24",
          "Distance27": "27",
          "Distance30": "30"
        },
        "Enhancements": {
          "Title": "Enhancements",
          "Add": "Add Enhancement",
          "ToggleDescription": "Expand or collapse description",
          "RequirementNotMetReactiveCasting": "Requirement not met: Rank C and casting time up to 1 action.",
          "RequirementNotMetCarefulCasting": "Requirement not met: the ability must have the Area characteristic.",
          "RequirementNotMetDestructiveCasting": "Requirement not met: the ability must have the Area characteristic.",
          "RequirementNotMetPiercing": "Requirement not met: the ability must have the Destruction characteristic."
        },
        "Enhancement": {
          "CaracteristicaAdicional": "Additional Characteristic",
          "CategoriaAdicional": "Additional Category",
          "ConjuracaoAdiada": "Delayed Casting",
          "ConjuracaoReativa": "Reactive Casting",
          "ConjuracaoCuidadosa": "Careful Casting",
          "DadoReikiAprimorado": "Enhanced Reiki Die",
          "ConjuracaoDestrutiva": "Destructive Casting",
          "Perfuracao": "Piercing"
        },
        "EnhancementDesc": {
          "CaracteristicaAdicional": "Allows the ability to gain one extra characteristic slot.",
          "CategoriaAdicional": "Allows the ability to gain one extra category slot.",
          "ConjuracaoAdiada": "Delay the casting to trigger under specific circumstances.",
          "ConjuracaoReativa": "Trigger casting as a reaction under defined conditions.",
          "ConjuracaoCuidadosa": "Reduced risk or collateral impact during casting.",
          "DadoReikiAprimorado": "Improve the reiki die used by this ability.",
          "ConjuracaoDestrutiva": "Boost destructive output at the cost of control.",
          "Perfuracao": "Increase penetration against defenses or resistances."
        },
        "Tags": {
          "Cuidadosa": "Careful",
          "Destrutiva": "Destructive",
          "Perfurante": "Piercing"
        },
        "Restrictions": {
          "Title": "Restriction",
          "Description": "Restriction",
          "Placeholder": "Describe the restriction...",
          "Advances": "Advances",
          "TargetLabel": "Characteristic",
          "TargetPlaceholder": "Select a characteristic",
          "TargetEmpty": "Unnamed characteristic"
        },
        "AdditionalSettings": {
          "Tab": "Additional Settings",
          "UseCastingAttribute": "Use actor casting attribute",
          "BonusLabel": "Bonus label",
          "NoneTitle": "No Additional Settings",
          "NoneDescription": "Add Destruction, Area or Condition to unlock cast settings.",
          "Attack": {
            "Title": "Attack",
            "OverrideToggle": "Use attack overrides",
            "Attribute": "Attribute",
            "ManualBonus": "Manual bonus",
            "AddBonus": "Add attack bonus"
          },
          "Secondary": {
            "Title": "Secondary Test",
            "Attribute": "Secondary attribute",
            "ManualDc": "Manual CDE",
            "UseManualDc": "Use manual CDE instead of actor CDE"
          },
          "Damage": {
            "Title": "Damage",
            "OverrideToggle": "Use damage override formula",
            "Formula": "Base formula",
            "Type": "Base type",
            "AddBonus": "Add damage part"
          }
        }
      },
      "AbilityCategory": {
        "CategoryLabel": "Category Effect",
        "CostLabel": "PC Cost",
        "NewName": "New Category Effect"
      }
    }
  }
}
